mathCore/ExamplePlots.py
mathCore/SpecialTensor.py
mathCore/__init__.py
mathCore/constants.py
mathCore/lambdas.py
mathCore/libs.py
mathCore/plot_tools.py
laapyCore-0.0.3.dist-info/METADATA
laapyCore-0.0.3.dist-info/WHEEL
laapyCore-0.0.3.dist-info/top_level.txt
laapyCore-0.0.3.dist-info/RECORD
