Metadata-Version: 2.1
Name: laapyCore
Version: 0.0.3
Summary: core utils
Home-page: https://github.com/Leikaab/laapyCore
Author: Leik Andre Asbjørnsen Butenschøn
Author-email: nordavindltd@gmail.com
License: UNKNOWN
Platform: UNKNOWN
Requires-Dist: numpy (~=1.23.0)
Requires-Dist: matplotlib (~=3.5)
Requires-Dist: pandas (~=1.4)
Requires-Dist: scipy (~=1.8)
Requires-Dist: sympy (~=1.1)
Provides-Extra: dev
Requires-Dist: pytest (>=7.1.2) ; extra == 'dev'
Requires-Dist: check-manifest (>=0.48) ; extra == 'dev'
Requires-Dist: twine (==4.0.1) ; extra == 'dev'
Requires-Dist: tox (==3.25.1) ; extra == 'dev'
